<theme>						
	<variant name="list-video, list-video-monochrome">					
		<aspectRatio name="1:1">				
			<view name="gamelist">			
				<video name="game-system-video">		
					<pos>0.655333333333333 0.440555555555556</pos>	
					<size>0.182222222222222 0.135555555555556</size>	
				</video>		
			</view>			
		</aspectRatio>				
		<aspectRatio name="5:4">				
			<view name="gamelist">			
				<video name="game-system-video">		
					<pos>0.655333333333333 0.425694444444444</pos>	
					<size>0.182222222222222 0.169444444444444</size>	
				</video>		
			</view>			
		</aspectRatio>				
		<aspectRatio name="4:3">				
			<view name="gamelist">			
				<video name="game-system-video">		
					<pos>0.655333333333333 0.420740740740741</pos>	
					<size>0.182222222222222 0.180740740740741</size>	
				</video>		
			</view>			
		</aspectRatio>				
		<aspectRatio name="3:2">				
			<view name="gamelist">			
				<video name="game-system-video">		
					<pos>0.655333333333333 0.410833333333333</pos>	
					<size>0.182222222222222 0.203333333333333</size>	
				</video>		
			</view>			
		</aspectRatio>				
		<aspectRatio name="16:10">				
			<view name="gamelist">			
				<video name="game-system-video">		
					<pos>0.655940972222222 0.409842592592593</pos>	
					<size>0.172731481481481 0.205592592592593</size>	
				</video>		
			</view>			
		</aspectRatio>				
		<aspectRatio name="16:9">				
			<view name="gamelist">			
				<video name="game-system-video">		
					<pos>0.657046875 0.409842592592593</pos>	
					<size>0.155458333333333 0.205592592592593</size>	
				</video>		
			</view>			
		</aspectRatio>				
		<aspectRatio name="19.5:9">				
			<view name="gamelist">			
				<video name="game-system-video">		
					<pos>0.658833333333333 0.409842592592593</pos>	
					<size>0.127555555555556 0.205592592592593</size>	
				</video>		
			</view>			
		</aspectRatio>				
		<aspectRatio name="21:9">				
			<view name="gamelist">			
				<video name="game-system-video">		
					<pos>0.659416666666667 0.409842592592593</pos>	
					<size>0.118444444444444 0.205592592592593</size>	
				</video>		
			</view>			
		</aspectRatio>				
	</variant>					
</theme>						
